mining_control/__init__.py
mining_control-0.0.1.dist-info/LICENSE
mining_control-0.0.1.dist-info/METADATA
mining_control-0.0.1.dist-info/WHEEL
mining_control-0.0.1.dist-info/top_level.txt
mining_control-0.0.1.dist-info/RECORD
